<properties>

    <property id="units" type="number">0</property>
    <property id="is12HourFormat" type="boolean">false</property>

    <property id="maxGoodSgvSetting" type="float">180</property>
    <property id="minGoodSgvSetting" type="float">80</property>

    <property id="maxGoodSgv" type="number">180</property>
    <property id="minGoodSgv" type="number">80</property>
    <property id="valuesInScreen" type="number">24</property>
    <property id="valuesGap" type="number">5</property>

    <property id="strColorBad" type="string">0xff0000</property>
    <property id="strColorGood" type="string">0x0000ff</property>

    <property id="colorBad" type="number">0xff0000</property>
    <property id="colorGood" type="number">0x0000ff</property>
</properties>
